{"nodes": [{"id": "interactivemap", "label": "InteractiveMap.tsx", "file_type": "code", "source_file": "components/InteractiveMap.tsx", "source_location": "L1"}], "edges": [{"source": "interactivemap", "target": "react", "relation": "imports_from", "confidence": "EXTRACTED", "source_file": "components/InteractiveMap.tsx", "source_location": "L3", "weight": 1.0}, {"source": "interactivemap", "target": "languagecontext", "relation": "imports_from", "confidence": "EXTRACTED", "source_file": "components/InteractiveMap.tsx", "source_location": "L4", "weight": 1.0}]}